types_aiobotocore_worklink/__init__.py
types_aiobotocore_worklink/__init__.pyi
types_aiobotocore_worklink/__main__.py
types_aiobotocore_worklink/client.py
types_aiobotocore_worklink/client.pyi
types_aiobotocore_worklink/literals.py
types_aiobotocore_worklink/literals.pyi
types_aiobotocore_worklink/py.typed
types_aiobotocore_worklink/type_defs.py
types_aiobotocore_worklink/type_defs.pyi
types_aiobotocore_worklink/version.py
types_aiobotocore_worklink-2.15.1.dist-info/LICENSE
types_aiobotocore_worklink-2.15.1.dist-info/METADATA
types_aiobotocore_worklink-2.15.1.dist-info/WHEEL
types_aiobotocore_worklink-2.15.1.dist-info/top_level.txt
types_aiobotocore_worklink-2.15.1.dist-info/RECORD
